{"sku": 461, "category": {"id": 52, "category": "Polygraphy / Printing equipment", "category_uz": "Poligrafiya / Tipografiya uskunalari", "category_ru": "\u041f\u043e\u043b\u0438\u0433\u0440\u0430\u0444\u0438\u0447\u0435\u0441\u043a\u043e\u0435 \u043e\u0431\u043e\u0440\u0443\u0434\u043e\u0432\u0430\u043d\u0438\u0435", "category_en": "Polygraphy / Printing equipment", "image": "https://api.uskunalar.uz/media/category_image/main_icon_vooS9RL.svg", "my_order": 35, "created_at": "2022-04-30T14:11:43.804000+05:00"}, "subcategory": {"id": 580, "image": "https://api.uskunalar.uz/media/sub_image/%D0%B3%D0%BB%D0%B0%D0%B2%D0%BD%D0%B0%D1%8F-5_5cjM0zE.png", "subcategory": "Printers", "subcategory_uz": "Printerlar", "subcategory_ru": "\u041f\u0440\u0438\u043d\u0442\u0435\u0440\u044b", "subcategory_en": "Printers", "my_order": 487, "created_at": "2022-05-07T13:58:02.930000+05:00", "category": 52, "category_uz": 52, "category_ru": 52, "category_en": 52}, "background": {"color": "Ko'k", "image": "https://api.uskunalar.uz/media/banner_back/blue.svg"}, "specifications": [{"id": 2928, "product_customer": "Model", "product_customer_uz": "Model", "product_customer_ru": "\u041c\u043e\u0434\u0435\u043b\u044c", "product_customer_en": "Model", "product_number": "US-C8000", "product_number_uz": "US-C8000", "product_number_ru": "US-C8000", "product_number_en": "US-C8000", "product_image": null}, {"id": 2937, "product_customer": "Formats", "product_customer_uz": "Formatlar", "product_customer_ru": "\u0424\u043e\u0440\u043c\u0430\u0442\u044b", "product_customer_en": "Formats", "product_number": "A3/A4/A5/B4/B5/B6", "product_number_uz": "A3/A4/A5/B4/B5/B6", "product_number_ru": "A3/A4/A5/B4/B5/B6", "product_number_en": "A3/A4/A5/B4/B5/B6", "product_image": null}, {"id": 2938, "product_customer": "Internal memory", "product_customer_uz": "Ichki xotira", "product_customer_ru": "\u0412\u043d\u0443\u0442\u0440\u0435\u043d\u043d\u044f\u044f \u043f\u0430\u043c\u044f\u0442\u044c", "product_customer_en": "Internal memory", "product_number": "500 GB", "product_number_uz": "500 GB", "product_number_ru": "500 \u0413\u0411", "product_number_en": "500 GB", "product_image": null}, {"id": 2939, "product_customer": "Working accuracy", "product_customer_uz": "Ishlash\u00a0aniqligi", "product_customer_ru": "\u0420\u0430\u0431\u043e\u0447\u0430\u044f \u0442\u043e\u0447\u043d\u043e\u0441\u0442\u044c", "product_customer_en": "Working accuracy", "product_number": "0.01 mm", "product_number_uz": "0.01 mm", "product_number_ru": "0.01 \u043c\u043c", "product_number_en": "0.01 mm", "product_image": null}, {"id": 2940, "product_customer": "Copy capacity", "product_customer_uz": "Nusxalash imoniyati", "product_customer_ru": "\u041a\u043e\u043b\u0438\u0447\u0435\u0441\u0442\u0432\u043e \u043a\u043e\u043f\u0438\u0439", "product_customer_en": "Copy capacity", "product_number": "up to 1-9999", "product_number_uz": "1-9999 gacha", "product_number_ru": "\u0434\u043e 1-9999", "product_number_en": "up to 1-9999", "product_image": null}, {"id": 2941, "product_customer": "Copy/print speed", "product_customer_uz": "Nusxalash/chop etish tezligi", "product_customer_ru": "\u0421\u043a\u043e\u0440\u043e\u0441\u0442\u044c \u043a\u043e\u043f\u0438\u0440\u043e\u0432\u0430\u043d\u0438\u044f/\u043f\u0435\u0447\u0430\u0442\u0438", "product_customer_en": "Copy/print speed", "product_number": "90-65 ppm", "product_number_uz": "90-65 ppm", "product_number_ru": "90-65 \u0441\u0442\u0440/\u043c\u0438\u043d", "product_number_en": "90-65 ppm", "product_image": null}], "images": [{"id": 1096, "image": "https://api.uskunalar.uz/media/products/c8000.png"}, {"id": 1098, "image": "https://api.uskunalar.uz/media/products/c8000_2.png"}, {"id": 1099, "image": "https://api.uskunalar.uz/media/products/c8000-3.jpg"}, {"id": 1100, "image": "https://api.uskunalar.uz/media/products/c8000-4.png"}, {"id": 1097, "image": "https://api.uskunalar.uz/media/products/c8000_1.jpg"}], "title": "Laser printer, BIZHUB PRESS US-C8000", "title_uz": "Lazerli printer, BIZHUB PRESS US-C8000", "title_ru": "\u041b\u0430\u0437\u0435\u0440\u043d\u044b\u0439 \u043f\u0440\u0438\u043d\u0442\u0435\u0440 BIZHUB PRESS US-C8000", "title_en": "Laser printer, BIZHUB PRESS US-C8000", "pdf": "https://api.uskunalar.uz/media/pdf/c8000.png", "city": null, "city_uz": null, "city_ru": null, "city_en": null, "CIP": true, "DAF": false, "EXW": true, "FCA": false, "price": "24700", "discount": "0", "inbox": "", "delivery": "\u041f\u043e\u0434 \u0437\u0430\u043a\u0430\u0437", "short_description": "<p style=\"text-align:justify\">There is probably no person who has not worked in this field in his life. Someone may have taken a photo, someone may have made a business card. The equipment presented below is the most modern technology for photocopying, printing business cards, booklets, catalogs, flyers and other products. This US-C8000 model large format laser printer equipment has printing, scanning, copying, folding, stapling, numbering and many other capabilities. This equipment can print at a speed of <span style=\"color:#e74c3c\">65 - 90</span> pages per minute with a resolution of <span style=\"color:#e74c3c\">1200 </span>DPI. This printer uses flash memory to .doc; .docx, xls; .xlsx; ppt; pptx; accepts data in pdf, jpeg and other widely used formats. In addition, this equipment has a working accuracy of 0.01 mm, as well as the ability to make double-sided copies at the same time.</p>", "short_description_uz": "<p style=\"text-align:justify\">Hayotida ushbu sohaga ishi tushmagan inson bo&#39;lmasa kerak. Kimdir surat chiqartirgan, yana kimdir vizitka tayyorlatgan bo&#39;lishi mumkin. Quyida taqdim etayotgan uskunamiz rasmlardan nusxa olish, vizitka, buklet, kataloglar chop etish, flayer va boshqa mahsulotlarni bosib chiqarish uchun mo&rsquo;ljallangan eng zamonaviy texnologiya hisoblanadi. Ushbu US-C8000 modeldagi yirik formatli lazerli printer uskunasi chop etish, skanerlash, nusxa olish, bukish, steplerlash, raqam bo&rsquo;yicha joylashtirish va boshqa bir qator imkoniyatlarga ega. Ushbu uskuna <span style=\"color:#e74c3c\">1200 </span>DPI aniqlik bilan daqiqasiga <span style=\"color:#e74c3c\">65 - 90</span> varoq tezligida chop etish imkoniyatiga ega. Ushbu printer flesh xotira yordamida .doc; .docx, xls; .xlsx; ppt; pptx; pdf, jpeg va boshqa keng qo&rsquo;llaniluvchi formatdagi ma&#39;lumotlarni qabul qiladi. Bundan tashqari, ushbu uskunaning ishlash aniqligi 0.01 mm, shuningdek, bir vaqtning o&#39;zida ikki tomonlama nusxa olish imkoniyatiga ega.</p>", "short_description_ru": "<p style=\"text-align:justify\">\u041d\u0430\u0432\u0435\u0440\u043d\u043e\u0435, \u043d\u0435\u0442 \u0447\u0435\u043b\u043e\u0432\u0435\u043a\u0430, \u043a\u043e\u0442\u043e\u0440\u044b\u0439 \u0432 \u0441\u0432\u043e\u0435\u0439 \u0436\u0438\u0437\u043d\u0438 \u043d\u0435 \u0440\u0430\u0431\u043e\u0442\u0430\u043b \u0432 \u044d\u0442\u043e\u0439 \u0441\u0444\u0435\u0440\u0435. \u0412\u043e\u0437\u043c\u043e\u0436\u043d\u043e, \u043a\u0442\u043e-\u0442\u043e \u0441\u0434\u0435\u043b\u0430\u043b \u0444\u043e\u0442\u043e, \u043a\u0442\u043e-\u0442\u043e \u0441\u0434\u0435\u043b\u0430\u043b \u0432\u0438\u0437\u0438\u0442\u043a\u0443. \u041f\u0440\u0435\u0434\u0441\u0442\u0430\u0432\u043b\u0435\u043d\u043d\u043e\u0435 \u043d\u0438\u0436\u0435 \u043e\u0431\u043e\u0440\u0443\u0434\u043e\u0432\u0430\u043d\u0438\u0435 &ndash; \u044d\u0442\u043e \u0441\u0430\u043c\u0430\u044f \u0441\u043e\u0432\u0440\u0435\u043c\u0435\u043d\u043d\u0430\u044f \u0442\u0435\u0445\u043d\u0438\u043a\u0430 \u0434\u043b\u044f \u043a\u0441\u0435\u0440\u043e\u043a\u043e\u043f\u0438\u0440\u043e\u0432\u0430\u043d\u0438\u044f, \u043f\u0435\u0447\u0430\u0442\u0438 \u0432\u0438\u0437\u0438\u0442\u043e\u043a, \u0431\u0443\u043a\u043b\u0435\u0442\u043e\u0432, \u043a\u0430\u0442\u0430\u043b\u043e\u0433\u043e\u0432, \u0444\u043b\u0430\u0435\u0440\u043e\u0432 \u0438 \u0434\u0440\u0443\u0433\u043e\u0439 \u043f\u0440\u043e\u0434\u0443\u043a\u0446\u0438\u0438. \u042d\u0442\u043e\u0442 \u0448\u0438\u0440\u043e\u043a\u043e\u0444\u043e\u0440\u043c\u0430\u0442\u043d\u044b\u0439 \u043b\u0430\u0437\u0435\u0440\u043d\u044b\u0439 \u043f\u0440\u0438\u043d\u0442\u0435\u0440 \u043c\u043e\u0434\u0435\u043b\u0438 US-C8000 \u0438\u043c\u0435\u0435\u0442 \u0444\u0443\u043d\u043a\u0446\u0438\u0438 \u043f\u0435\u0447\u0430\u0442\u0438, \u0441\u043a\u0430\u043d\u0438\u0440\u043e\u0432\u0430\u043d\u0438\u044f, \u043a\u043e\u043f\u0438\u0440\u043e\u0432\u0430\u043d\u0438\u044f, \u0444\u0430\u043b\u044c\u0446\u043e\u0432\u043a\u0438, \u0441\u0448\u0438\u0432\u0430\u043d\u0438\u044f, \u043d\u0443\u043c\u0435\u0440\u0430\u0446\u0438\u0438 \u0438 \u043c\u043d\u043e\u0433\u0438\u0445 \u0434\u0440\u0443\u0433\u0438\u0445 \u0444\u0443\u043d\u043a\u0446\u0438\u0439. \u042d\u0442\u043e \u043e\u0431\u043e\u0440\u0443\u0434\u043e\u0432\u0430\u043d\u0438\u0435 \u043c\u043e\u0436\u0435\u0442 \u043f\u0435\u0447\u0430\u0442\u0430\u0442\u044c \u0441\u043e \u0441\u043a\u043e\u0440\u043e\u0441\u0442\u044c\u044e <span style=\"color:#e74c3c\">65 &ndash; 90</span> \u0441\u0442\u0440\u0430\u043d\u0438\u0446 \u0432 \u043c\u0438\u043d\u0443\u0442\u0443 \u0441 \u0440\u0430\u0437\u0440\u0435\u0448\u0435\u043d\u0438\u0435\u043c <span style=\"color:#e74c3c\">1200 </span>DPI. \u042d\u0442\u043e\u0442 \u043f\u0440\u0438\u043d\u0442\u0435\u0440 \u0438\u0441\u043f\u043e\u043b\u044c\u0437\u0443\u0435\u0442 \u0444\u043b\u044d\u0448-\u043f\u0430\u043c\u044f\u0442\u044c \u0434\u043b\u044f .doc; .docx, xls; .xlsx; \u043f\u043f; \u043f\u0442\u043a\u0441; \u043f\u0440\u0438\u043d\u0438\u043c\u0430\u0435\u0442 \u0434\u0430\u043d\u043d\u044b\u0435 \u0432 pdf, jpeg \u0438 \u0434\u0440\u0443\u0433\u0438\u0445 \u0448\u0438\u0440\u043e\u043a\u043e \u0438\u0441\u043f\u043e\u043b\u044c\u0437\u0443\u0435\u043c\u044b\u0445 \u0444\u043e\u0440\u043c\u0430\u0442\u0430\u0445. \u041a\u0440\u043e\u043c\u0435 \u0442\u043e\u0433\u043e, \u044d\u0442\u043e \u043e\u0431\u043e\u0440\u0443\u0434\u043e\u0432\u0430\u043d\u0438\u0435 \u0438\u043c\u0435\u0435\u0442 \u0440\u0430\u0431\u043e\u0447\u0443\u044e \u0442\u043e\u0447\u043d\u043e\u0441\u0442\u044c 0,01 \u043c\u043c, \u0430 \u0442\u0430\u043a\u0436\u0435 \u0432\u043e\u0437\u043c\u043e\u0436\u043d\u043e\u0441\u0442\u044c \u0434\u0435\u043b\u0430\u0442\u044c \u0434\u0432\u0443\u0441\u0442\u043e\u0440\u043e\u043d\u043d\u0438\u0435 \u043a\u043e\u043f\u0438\u0438 \u043e\u0434\u043d\u043e\u0432\u0440\u0435\u043c\u0435\u043d\u043d\u043e.</p>", "short_description_en": "<p style=\"text-align:justify\">There is probably no person who has not worked in this field in his life. Someone may have taken a photo, someone may have made a business card. The equipment presented below is the most modern technology for photocopying, printing business cards, booklets, catalogs, flyers and other products. This US-C8000 model large format laser printer equipment has printing, scanning, copying, folding, stapling, numbering and many other capabilities. This equipment can print at a speed of <span style=\"color:#e74c3c\">65 - 90</span> pages per minute with a resolution of <span style=\"color:#e74c3c\">1200 </span>DPI. This printer uses flash memory to .doc; .docx, xls; .xlsx; ppt; pptx; accepts data in pdf, jpeg and other widely used formats. In addition, this equipment has a working accuracy of 0.01 mm, as well as the ability to make double-sided copies at the same time.</p>", "long_description": "<p><strong>Laser printer, BIZHUB PRESS US-C8000.</strong></p>\r\n\r\n<p><strong>Technical indicators of the equipment:</strong></p>\r\n\r\n<ul>\r\n\t<li>Model: US-C8000.</li>\r\n\t<li>Print quality: 1200 dpi x 1200 dpi.&nbsp;</li>\r\n\t<li>Formats: A3 / A4 / A5 / B4 / B5 / B6.</li>\r\n\t<li>Internal memory: 500 GB.</li>\r\n\t<li>Working accuracy: 0.01 mm.</li>\r\n\t<li>Paper acceptance: 52-300 g.</li>\r\n\t<li>Copy/Print Speed: 90-65 ppm.</li>\r\n\t<li>Copy capacity: up to 1-9999.</li>\r\n\t<li>Number of paper sections: 4.</li>\r\n\t<li>Copy type: back-to-front simultaneously.</li>\r\n\t<li>Operating system: Windows 2000/XP/XP64, Windows VISTA 32/64, Windows 7 32/64, Server 2000 / 2003 / 2003 x 64 / 2008 / 2008 x 64 / 2008 (R2), Mac 9.x/10.x, Unix/Linux/Citrix.</li>\r\n\t<li>Country of manufacture: China.</li>\r\n</ul>", "long_description_uz": "<p><strong>Lazerli printer, BIZHUB PRESS US-C8000.&nbsp;</strong></p>\r\n\r\n<p><strong>Uskunaning texnik ko&rsquo;rsatkichlari:</strong></p>\r\n\r\n<ul>\r\n\t<li>Model: US-C8000.</li>\r\n\t<li>Chop etish sifati: 1200 dpi x 1200 dpi.&nbsp;</li>\r\n\t<li>Formatlar:&nbsp;A3 / A4 / A5 / B4 / B5 / B6.</li>\r\n\t<li>Ichki xotira: 500 GB.</li>\r\n\t<li>Ishlash&nbsp;aniqligi: 0,01 mm.</li>\r\n\t<li>Qog&rsquo;oz qabul qilish: 52-300 g.</li>\r\n\t<li>Nusxalash/chop etish tezligi: 90-65 varoq / daqiqasiga.</li>\r\n\t<li>Nusxalash imoniyati: 1-9999 gacha.</li>\r\n\t<li>Qog&rsquo;oz turuvchi bo&rsquo;lmalar soni: 4 ta.</li>\r\n\t<li>Nusxa olish turi: orqa oldi bir vaqtda.</li>\r\n\t<li>Operatsion tizim:&nbsp;Windows 2000/XP/XP64, Windows VISTA 32/64, Windows 7 32/64, Server 2000 / 2003 / 2003 x&nbsp;64 / 2008 / 2008x64/2008 (R2), Mac 9.x/10.x, Unix/Linux/Citrix.</li>\r\n\t<li>Ishlab chiqarilgan davlat: Xitoy.</li>\r\n</ul>", "long_description_ru": "<p><strong>\u041b\u0430\u0437\u0435\u0440\u043d\u044b\u0439 \u043f\u0440\u0438\u043d\u0442\u0435\u0440 BIZHUB PRESS US-C8000.</strong></p>\r\n\r\n<p><strong>\u0422\u0435\u0445\u043d\u0438\u0447\u0435\u0441\u043a\u0438\u0435 \u043f\u043e\u043a\u0430\u0437\u0430\u0442\u0435\u043b\u0438 \u043e\u0431\u043e\u0440\u0443\u0434\u043e\u0432\u0430\u043d\u0438\u044f:</strong></p>\r\n\r\n<ul>\r\n\t<li>\u041c\u043e\u0434\u0435\u043b\u044c: US-C8000.</li>\r\n\t<li>\u041a\u0430\u0447\u0435\u0441\u0442\u0432\u043e \u043f\u0435\u0447\u0430\u0442\u0438: 1200 x 1200 dpi.</li>\r\n\t<li>\u0424\u043e\u0440\u043c\u0430\u0442\u044b: \u04103 / \u04104 / \u04105 / \u04124 / \u04125 / \u04126.</li>\r\n\t<li>\u0412\u043d\u0443\u0442\u0440\u0435\u043d\u043d\u044f\u044f \u043f\u0430\u043c\u044f\u0442\u044c: 500 \u0413\u0411.</li>\r\n\t<li>\u0420\u0430\u0431\u043e\u0447\u0430\u044f \u0442\u043e\u0447\u043d\u043e\u0441\u0442\u044c: 0,01 \u043c\u043c.</li>\r\n\t<li>\u041f\u0440\u0438\u0435\u043c\u043a\u0430 \u0431\u0443\u043c\u0430\u0433\u0438: 52-300 \u0433.</li>\r\n\t<li>\u0421\u043a\u043e\u0440\u043e\u0441\u0442\u044c \u043a\u043e\u043f\u0438\u0440\u043e\u0432\u0430\u043d\u0438\u044f/\u043f\u0435\u0447\u0430\u0442\u0438: 90-65 \u0441\u0442\u0440/\u043c\u0438\u043d.</li>\r\n\t<li>\u041a\u043e\u043b\u0438\u0447\u0435\u0441\u0442\u0432\u043e \u043a\u043e\u043f\u0438\u0439: \u0434\u043e 1-9999.</li>\r\n\t<li>\u041a\u043e\u043b\u0438\u0447\u0435\u0441\u0442\u0432\u043e \u0431\u0443\u043c\u0430\u0436\u043d\u044b\u0445 \u0441\u0435\u043a\u0446\u0438\u0439: 4.</li>\r\n\t<li>\u0422\u0438\u043f \u043a\u043e\u043f\u0438\u0440\u043e\u0432\u0430\u043d\u0438\u044f: \u043e\u0434\u043d\u043e\u0432\u0440\u0435\u043c\u0435\u043d\u043d\u0430\u044f \u043e\u0431\u0440\u0430\u0442\u043d\u0430\u044f \u0441\u0442\u043e\u0440\u043e\u043d\u0430 \u0432\u043f\u0435\u0440\u0435\u0434.</li>\r\n\t<li>\u041e\u043f\u0435\u0440\u0430\u0446\u0438\u043e\u043d\u043d\u0430\u044f \u0441\u0438\u0441\u0442\u0435\u043c\u0430: Windows 2000/XP/XP64, Windows VISTA 32/64, Windows 7 32/64, Server 2000/2003/2003 x 64/2008/2008 x 64/2008 (R2), Mac 9.x/10.x, Unix/Linux/Citrix.</li>\r\n\t<li>\u0421\u0442\u0440\u0430\u043d\u0430 \u043f\u0440\u043e\u0438\u0437\u0432\u043e\u0434\u0438\u0442\u0435\u043b\u044c: \u041a\u0438\u0442\u0430\u0439.</li>\r\n</ul>", "long_description_en": "<p><strong>Laser printer, BIZHUB PRESS US-C8000.</strong></p>\r\n\r\n<p><strong>Technical indicators of the equipment:</strong></p>\r\n\r\n<ul>\r\n\t<li>Model: US-C8000.</li>\r\n\t<li>Print quality: 1200 dpi x 1200 dpi.&nbsp;</li>\r\n\t<li>Formats: A3 / A4 / A5 / B4 / B5 / B6.</li>\r\n\t<li>Internal memory: 500 GB.</li>\r\n\t<li>Working accuracy: 0.01 mm.</li>\r\n\t<li>Paper acceptance: 52-300 g.</li>\r\n\t<li>Copy/Print Speed: 90-65 ppm.</li>\r\n\t<li>Copy capacity: up to 1-9999.</li>\r\n\t<li>Number of paper sections: 4.</li>\r\n\t<li>Copy type: back-to-front simultaneously.</li>\r\n\t<li>Operating system: Windows 2000/XP/XP64, Windows VISTA 32/64, Windows 7 32/64, Server 2000 / 2003 / 2003 x 64 / 2008 / 2008 x 64 / 2008 (R2), Mac 9.x/10.x, Unix/Linux/Citrix.</li>\r\n\t<li>Country of manufacture: China.</li>\r\n</ul>", "price_title": null, "price_title_uz": null, "price_title_ru": null, "price_title_en": null, "price_image": null, "price_short_description": null, "price_short_description_uz": null, "price_short_description_ru": null, "price_short_description_en": null, "price_long_description": null, "price_long_description_uz": null, "price_long_description_ru": null, "price_long_description_en": null, "video": null, "view_count": 1844, "created_at": "2022-12-01T14:45:37.137000+05:00", "country": 1, "product_id": 879}