{"sku": 522, "category": {"id": 76, "category": "Wood processing and furniture manufacturing industry equipment", "category_uz": "Yog`ochni qayta ishlash  va mebel ishlab chiqarish uskunalari", "category_ru": "\u041e\u0431\u043e\u0440\u0443\u0434\u043e\u0432\u0430\u043d\u0438\u0435 \u0434\u043b\u044f \u0434\u0435\u0440\u0435\u0432\u043e\u043e\u0431\u0440\u0430\u0431\u0430\u0442\u044b\u0432\u0430\u044e\u0449\u0435\u0439 \u0438 \u043c\u0435\u0431\u0435\u043b\u044c\u043d\u043e\u0439 \u043f\u0440\u043e\u043c\u044b\u0448\u043b\u0435\u043d\u043d\u043e\u0441\u0442\u0438", "category_en": "Wood processing and furniture manufacturing industry equipment", "image": "https://api.uskunalar.uz/media/category_image/furniture.svg", "my_order": 6, "created_at": "2022-05-24T12:32:09.377000+05:00"}, "subcategory": {"id": 726, "image": null, "subcategory": "Grinding machines", "subcategory_uz": "Yog'och silliqlash uskunalari", "subcategory_ru": "\u0428\u043b\u0438\u0444\u043e\u0432\u0430\u043b\u044c\u043d\u044b\u0439 \u0441\u0442\u0430\u043d\u043a\u0438", "subcategory_en": "Grinding machines", "my_order": 655, "created_at": "2022-11-01T14:54:45.087000+05:00", "category": 76, "category_uz": 76, "category_ru": 76, "category_en": 76}, "background": {"color": "Olovrang", "image": "https://api.uskunalar.uz/media/banner_back/orange.svg"}, "specifications": [{"id": 3330, "product_customer": "Working thickness", "product_customer_uz": "Ish qalinligi", "product_customer_ru": "\u0420\u0430\u0431\u043e\u0447\u0430\u044f \u0442\u043e\u043b\u0449\u0438\u043d\u0430", "product_customer_en": "Working thickness", "product_number": "2.5 ~ 100 mm", "product_number_uz": "2.5 ~ 100 mm", "product_number_ru": "2.5 ~ 100 \u043c\u043c", "product_number_en": "2.5 ~ 100 mm", "product_image": null}, {"id": 3331, "product_customer": "Feed speed", "product_customer_uz": "Ishlash tezligi", "product_customer_ru": "\u0421\u043a\u043e\u0440\u043e\u0441\u0442\u044c \u043f\u043e\u0434\u0430\u0447\u0438", "product_customer_en": "Feed speed", "product_number": "6 ~ 30 m / min", "product_number_uz": "6 ~ 30 m / min", "product_number_ru": "6 ~ 30 \u043c / \u043c\u0438\u043d", "product_number_en": "6 ~ 30 m / min", "product_image": null}, {"id": 3332, "product_customer": "Dimensions", "product_customer_uz": "O'lchamlari", "product_customer_ru": "\u0420\u0430\u0437\u043c\u0435\u0440\u044b", "product_customer_en": "Dimensions", "product_number": "2200 x 2650 x 2100 mm", "product_number_uz": "2200 x 2650 x 2100 mm", "product_number_ru": "2200 x 2650 x 2100 \u043c\u043c", "product_number_en": "2200 x 2650 x 2100 mm", "product_image": null}, {"id": 3333, "product_customer": "Weight", "product_customer_uz": "Og'irligi", "product_customer_ru": "\u0412\u0435\u0441", "product_customer_en": "Weight", "product_number": "3600 kg", "product_number_uz": "3600 kg", "product_number_ru": "3600 \u043a\u0433", "product_number_en": "3600 kg", "product_image": null}, {"id": 3326, "product_customer": "Model", "product_customer_uz": "Model", "product_customer_ru": "\u041c\u043e\u0434\u0435\u043b\u044c", "product_customer_en": "Model", "product_number": "US-R-RP1300", "product_number_uz": "US-R-RP1300", "product_number_ru": "US-R-RP1300", "product_number_en": "US-R-RP1300", "product_image": null}, {"id": 3327, "product_customer": "Power (KW)", "product_customer_uz": "Quvvat (KW)", "product_customer_ru": "\u041c\u043e\u0449\u043d\u043e\u0441\u0442\u044c (KW)", "product_customer_en": "Power (KW)", "product_number": "63.55 KW", "product_number_uz": "63.55 KW", "product_number_ru": "63.55 KW", "product_number_en": "63.55 KW", "product_image": null}, {"id": 3328, "product_customer": "Sanding length", "product_customer_uz": "Silliqlash uzunligi", "product_customer_ru": "\u0414\u043b\u0438\u043d\u0430 \u0448\u043b\u0438\u0444\u043e\u0432\u043a\u0438", "product_customer_en": "Sanding length", "product_number": "\u2265 640 mm", "product_number_uz": "\u2265 640 mm", "product_number_ru": "\u2265 640 \u043c\u043c", "product_number_en": "\u2265 640 mm", "product_image": null}, {"id": 3329, "product_customer": "Sanding width", "product_customer_uz": "Silliqlash\u00a0kengligi", "product_customer_ru": "\u0428\u0438\u0440\u0438\u043d\u0430 \u0448\u043b\u0438\u0444\u043e\u0432\u0430\u043d\u0438\u044f", "product_customer_en": "Sanding width", "product_number": "40 ~ 1300 mm", "product_number_uz": "40 ~ 1300 mm", "product_number_ru": "40 ~ 1300 \u043c\u043c", "product_number_en": "40 ~ 1300 mm", "product_image": null}], "images": [{"id": 1322, "image": "https://api.uskunalar.uz/media/products/r_rp1300.png"}, {"id": 1323, "image": "https://api.uskunalar.uz/media/products/r_rp1300_1.png"}, {"id": 1324, "image": "https://api.uskunalar.uz/media/products/r_rp1300_2.jpg"}, {"id": 1325, "image": "https://api.uskunalar.uz/media/products/r_rp1300_3.jpg"}, {"id": 1510, "image": "https://api.uskunalar.uz/media/products/r_rp1300_4.jpg"}, {"id": 1511, "image": "https://api.uskunalar.uz/media/products/r_rp1300_5.jpg"}], "title": "Wide belt sanding machine US-R-RP1300", "title_uz": "Keng tasmali silliqlash uskunasi US-R-RP1300", "title_ru": "\u0428\u0438\u0440\u043e\u043a\u043e\u043b\u0435\u043d\u0442\u043e\u0447\u043d\u044b\u0439 \u0448\u043b\u0438\u0444\u043e\u0432\u0430\u043b\u044c\u043d\u044b\u0439 \u0441\u0442\u0430\u043d\u043e\u043a US-R-RP1300", "title_en": "Wide belt sanding machine US-R-RP1300", "pdf": "https://api.uskunalar.uz/media/pdf/r_rp1300.png", "city": null, "city_uz": null, "city_ru": null, "city_en": null, "CIP": false, "DAF": false, "EXW": true, "FCA": false, "price": "550", "discount": "0", "inbox": "", "delivery": "\u041f\u043e\u0434 \u0437\u0430\u043a\u0430\u0437", "short_description": "<p style=\"text-align:justify\">This US-R-RP1300 model wide belt sanding machine consumes a total of <span style=\"color:#e74c3c\">63.55 </span>KW per hour and also operates at an air pressure of 0.55 mpa. In addition, the wood sanding length of this equipment is <span style=\"color:#e74c3c\">640 </span>mm, and the sanding width is <span style=\"color:#e74c3c\">40 ~ 1300&nbsp;</span>mm. Also, the speed of the first wood sanding belt in this equipment is <span style=\"color:#e74c3c\">20 </span>meters per second, and the speed of the second belt is <span style=\"color:#e74c3c\">18.5 </span>meters per second. The size of the grinding belt of this equipment is <span style=\"color:#e74c3c\">1320 x 2200</span> mm, and the total working capacity of the equipment is <span style=\"color:#e74c3c\">6 ~ 30</span> meters per minute. The total dimensions of the equipment are<span style=\"color:#e74c3c\"> 2200 x 2650 x 2100</span> mm and the weight is <span style=\"color:#e74c3c\">3600 </span>kg.</p>", "short_description_uz": "<p style=\"text-align:justify\">Ushbu US-R-RP1300 modeldagi keng tasmali silliqlash uskunasi soatiga umumiy <span style=\"color:#e74c3c\">63.55 </span>KW quvvat sarflaydi, shuningdek, 0.55 mpa havo bosimida ishlaydi.&nbsp;Bundan tashqari, ushbu uskunada yog&#39;och silliqlash uzunligi <span style=\"color:#e74c3c\">640 </span>mm bo&#39;lsa, silliqlash kengligi <span style=\"color:#e74c3c\">40 ~ 1300</span> mmni tashkil etadi.&nbsp;Shuningdek, ushbu uskunadagi birinchi yog&#39;och silliqlovchi tasma tezligi soniyasiga <span style=\"color:#e74c3c\">20 </span>metr, ikkinchi tasma tezligi esa soniyasiga <span style=\"color:#e74c3c\">18.5 </span>metr hisoblanadi.&nbsp;Ushbu uskunaning silliqlovchi tasma o&#39;lchamlari <span style=\"color:#e74c3c\">1320 x 2200</span> mm bo&#39;lib, uskunaning umumiy ishlash imkoniyati daqiqasiga <span style=\"color:#e74c3c\">6 ~ 30</span> metrni tashkil etadi. &nbsp;Uskunaning umumiy o&#39;lchamlari <span style=\"color:#e74c3c\">2200 x 2650 x 2100</span> mm hamda og&#39;irligi &nbsp;<span style=\"color:#e74c3c\">3600 </span>kgni tashkil etadi.</p>", "short_description_ru": "<p style=\"text-align:justify\">\u042d\u0442\u0430 \u0448\u0438\u0440\u043e\u043a\u043e\u043b\u0435\u043d\u0442\u043e\u0447\u043d\u0430\u044f \u0448\u043b\u0438\u0444\u043e\u0432\u0430\u043b\u044c\u043d\u0430\u044f \u043c\u0430\u0448\u0438\u043d\u0430 \u043c\u043e\u0434\u0435\u043b\u0438 US-R-RP1300 \u043f\u043e\u0442\u0440\u0435\u0431\u043b\u044f\u0435\u0442 \u0432 \u043e\u0431\u0449\u0435\u0439 \u0441\u043b\u043e\u0436\u043d\u043e\u0441\u0442\u0438 <span style=\"color:#e74c3c\">63,55</span> \u043a\u0412\u0442 \u0432 \u0447\u0430\u0441 \u0438 \u0442\u0430\u043a\u0436\u0435 \u0440\u0430\u0431\u043e\u0442\u0430\u0435\u0442 \u043f\u0440\u0438 \u0434\u0430\u0432\u043b\u0435\u043d\u0438\u0438 \u0432\u043e\u0437\u0434\u0443\u0445\u0430 0,55 \u041c\u041f\u0430. \u041a\u0440\u043e\u043c\u0435 \u0442\u043e\u0433\u043e, \u0434\u043b\u0438\u043d\u0430 \u0448\u043b\u0438\u0444\u043e\u0432\u0430\u043d\u0438\u044f \u0434\u0440\u0435\u0432\u0435\u0441\u0438\u043d\u044b \u044d\u0442\u0438\u043c \u043e\u0431\u043e\u0440\u0443\u0434\u043e\u0432\u0430\u043d\u0438\u0435\u043c \u0441\u043e\u0441\u0442\u0430\u0432\u043b\u044f\u0435\u0442 <span style=\"color:#e74c3c\">640 </span>\u043c\u043c, \u0430 \u0448\u0438\u0440\u0438\u043d\u0430 \u0448\u043b\u0438\u0444\u043e\u0432\u0430\u043d\u0438\u044f \u0441\u043e\u0441\u0442\u0430\u0432\u043b\u044f\u0435\u0442 <span style=\"color:#e74c3c\">40 ~ 1300</span> \u043c\u043c. \u041a\u0440\u043e\u043c\u0435 \u0442\u043e\u0433\u043e, \u0441\u043a\u043e\u0440\u043e\u0441\u0442\u044c \u043f\u0435\u0440\u0432\u043e\u0439 \u043b\u0435\u043d\u0442\u044b \u0434\u043b\u044f \u0448\u043b\u0438\u0444\u043e\u0432\u043a\u0438 \u0434\u0440\u0435\u0432\u0435\u0441\u0438\u043d\u044b \u0432 \u044d\u0442\u043e\u043c \u043e\u0431\u043e\u0440\u0443\u0434\u043e\u0432\u0430\u043d\u0438\u0438 \u0441\u043e\u0441\u0442\u0430\u0432\u043b\u044f\u0435\u0442 <span style=\"color:#e74c3c\">20 </span>\u043c\u0435\u0442\u0440\u043e\u0432 \u0432 \u0441\u0435\u043a\u0443\u043d\u0434\u0443, \u0430 \u0441\u043a\u043e\u0440\u043e\u0441\u0442\u044c \u0432\u0442\u043e\u0440\u043e\u0439 \u043b\u0435\u043d\u0442\u044b &ndash;&nbsp;<span style=\"color:#e74c3c\">18,5 </span>\u043c\u0435\u0442\u0440\u043e\u0432 \u0432 \u0441\u0435\u043a\u0443\u043d\u0434\u0443. \u0420\u0430\u0437\u043c\u0435\u0440 \u0448\u043b\u0438\u0444\u043e\u0432\u0430\u043b\u044c\u043d\u043e\u0439 \u043b\u0435\u043d\u0442\u044b \u044d\u0442\u043e\u0433\u043e \u043e\u0431\u043e\u0440\u0443\u0434\u043e\u0432\u0430\u043d\u0438\u044f \u0441\u043e\u0441\u0442\u0430\u0432\u043b\u044f\u0435\u0442 <span style=\"color:#e74c3c\">1320 \u0445 2200 </span>\u043c\u043c, \u0430 \u043e\u0431\u0449\u0430\u044f \u043f\u0440\u043e\u0438\u0437\u0432\u043e\u0434\u0438\u0442\u0435\u043b\u044c\u043d\u043e\u0441\u0442\u044c \u043e\u0431\u043e\u0440\u0443\u0434\u043e\u0432\u0430\u043d\u0438\u044f \u0441\u043e\u0441\u0442\u0430\u0432\u043b\u044f\u0435\u0442 <span style=\"color:#e74c3c\">6 ~ 30</span> \u043c\u0435\u0442\u0440\u043e\u0432 \u0432 \u043c\u0438\u043d\u0443\u0442\u0443. \u0413\u0430\u0431\u0430\u0440\u0438\u0442\u043d\u044b\u0435 \u0440\u0430\u0437\u043c\u0435\u0440\u044b \u043e\u0431\u043e\u0440\u0443\u0434\u043e\u0432\u0430\u043d\u0438\u044f \u0441\u043e\u0441\u0442\u0430\u0432\u043b\u044f\u044e\u0442 <span style=\"color:#e74c3c\">2200 \u0445 2650 \u0445 2100 </span>\u043c\u043c, \u0430 \u0432\u0435\u0441 <span style=\"color:#e74c3c\">3600 </span>\u043a\u0433.</p>", "short_description_en": "<p style=\"text-align:justify\">This US-R-RP1300 model wide belt sanding machine consumes a total of <span style=\"color:#e74c3c\">63.55 </span>KW per hour and also operates at an air pressure of 0.55 mpa. In addition, the wood sanding length of this equipment is <span style=\"color:#e74c3c\">640 </span>mm, and the sanding width is <span style=\"color:#e74c3c\">40 ~ 1300&nbsp;</span>mm. Also, the speed of the first wood sanding belt in this equipment is <span style=\"color:#e74c3c\">20 </span>meters per second, and the speed of the second belt is <span style=\"color:#e74c3c\">18.5 </span>meters per second. The size of the grinding belt of this equipment is <span style=\"color:#e74c3c\">1320 x 2200</span> mm, and the total working capacity of the equipment is <span style=\"color:#e74c3c\">6 ~ 30</span> meters per minute. The total dimensions of the equipment are<span style=\"color:#e74c3c\"> 2200 x 2650 x 2100</span> mm and the weight is <span style=\"color:#e74c3c\">3600 </span>kg.</p>", "long_description": "<p><strong>Wide belt sanding machine US-R-RP1300.</strong></p>\r\n\r\n<p><strong>Technical parameters of the equipment:</strong></p>\r\n\r\n<ul>\r\n\t<li>Model: US-R-RP1300.</li>\r\n\t<li>Total motor power: 63.55 KW.</li>\r\n\t<li>The length of sanding: &ge; 640 mm.</li>\r\n\t<li>The width of&nbsp;&nbsp; &nbsp;sanding: 40 ~ 1300 mm.</li>\r\n\t<li>Working thickness: 2.5 ~ 100 mm.</li>\r\n\t<li>No.1 abrasive belt speed: 20 m / sec.</li>\r\n\t<li>No.2 abrasive belt speed: 18.5 m / sec.</li>\r\n\t<li>Feed speed: 6 ~ 30 m / min.</li>\r\n\t<li>Size of abrasive belt: 1320 x 2200 mm.</li>\r\n\t<li>Working air pressure: 0.55 mpa.</li>\r\n\t<li>Consumption of compressed air: 0.3 m&sup3; / min.</li>\r\n\t<li>Speed of sucked air: 25 - 30 m / s.</li>\r\n\t<li>Overall dimension: 2200 x 2650 x 2100 mm.</li>\r\n\t<li>Net weight: 3600 kg.</li>\r\n</ul>", "long_description_uz": "<p><strong>Keng tasmali silliqlash uskunasi US-R-RP1300.</strong></p>\r\n\r\n<p><strong>Uskunaning texnik ko&rsquo;rsatkichlari:</strong></p>\r\n\r\n<ul>\r\n\t<li>Model:&nbsp;US-R-RP1300.</li>\r\n\t<li>Dvigatelning umumiy quvvati: 63.55 KW.</li>\r\n\t<li>Silliqlash uzunligi: &ge; 640 mm.</li>\r\n\t<li>Silliqlash&nbsp;kengligi:&nbsp;40 ~ 1300 mm.</li>\r\n\t<li>Ish qalinligi: 2,5 ~ 100 mm.</li>\r\n\t<li>1-tasma&nbsp;tezligi: 20 m / sek.</li>\r\n\t<li>2-tasma&nbsp;tezligi: 18.5 m / sek.</li>\r\n\t<li>Ishlash tezligi:&nbsp;6 ~ 30 m / min.</li>\r\n\t<li>Tasma&nbsp;o&#39;lchami:&nbsp;1320 x 2200 mm.</li>\r\n\t<li>Ishchi havo bosimi: 0,55 mpa.</li>\r\n\t<li>Siqilgan havo iste&#39;moli: 0,3 m<sup>3</sup>&nbsp;/ min.</li>\r\n\t<li>So&#39;rilgan havo tezligi: 25 - 30 m / sek.</li>\r\n\t<li>Umumiy o&#39;lchamlari: 2200 x 2650 x 2100 mm.</li>\r\n\t<li>Og&#39;irligi:&nbsp;3600 kg.</li>\r\n</ul>", "long_description_ru": "<p><strong>\u0428\u0438\u0440\u043e\u043a\u043e\u043b\u0435\u043d\u0442\u043e\u0447\u043d\u044b\u0439 \u0448\u043b\u0438\u0444\u043e\u0432\u0430\u043b\u044c\u043d\u044b\u0439 \u0441\u0442\u0430\u043d\u043e\u043a US-R-RP1300.</strong></p>\r\n\r\n<p><strong>\u0422\u0435\u0445\u043d\u0438\u0447\u0435\u0441\u043a\u0438\u0435 \u043f\u043e\u043a\u0430\u0437\u0430\u0442\u0435\u043b\u0438 \u043e\u0431\u043e\u0440\u0443\u0434\u043e\u0432\u0430\u043d\u0438\u044f:</strong></p>\r\n\r\n<ul>\r\n\t<li>\u041c\u043e\u0434\u0435\u043b\u044c: US-R-RP1300.</li>\r\n\t<li>\u0421\u0443\u043c\u043c\u0430\u0440\u043d\u0430\u044f \u043c\u043e\u0449\u043d\u043e\u0441\u0442\u044c \u0434\u0432\u0438\u0433\u0430\u0442\u0435\u043b\u044f: 63,55 \u043a\u0412\u0442.</li>\r\n\t<li>\u0414\u043b\u0438\u043d\u0430 \u0448\u043b\u0438\u0444\u043e\u0432\u043a\u0438: &ge; 640 \u043c\u043c.</li>\r\n\t<li>\u0428\u0438\u0440\u0438\u043d\u0430 \u0448\u043b\u0438\u0444\u043e\u0432\u0430\u043d\u0438\u044f: 40 ~ 1300 \u043c\u043c.</li>\r\n\t<li>\u0420\u0430\u0431\u043e\u0447\u0430\u044f \u0442\u043e\u043b\u0449\u0438\u043d\u0430: 2,5 ~ 100 \u043c\u043c.</li>\r\n\t<li>\u0421\u043a\u043e\u0440\u043e\u0441\u0442\u044c \u0430\u0431\u0440\u0430\u0437\u0438\u0432\u043d\u043e\u0439 \u043b\u0435\u043d\u0442\u044b \u21161: 20 \u043c / \u0441\u0435\u043a.</li>\r\n\t<li>\u0421\u043a\u043e\u0440\u043e\u0441\u0442\u044c \u0430\u0431\u0440\u0430\u0437\u0438\u0432\u043d\u043e\u0439 \u043b\u0435\u043d\u0442\u044b \u21162: 18,5 \u043c / \u0441\u0435\u043a.</li>\r\n\t<li>\u0421\u043a\u043e\u0440\u043e\u0441\u0442\u044c \u043f\u043e\u0434\u0430\u0447\u0438: 6 ~ 30 \u043c/\u043c\u0438\u043d.</li>\r\n\t<li>\u0420\u0430\u0437\u043c\u0435\u0440 \u0430\u0431\u0440\u0430\u0437\u0438\u0432\u043d\u043e\u0439 \u043b\u0435\u043d\u0442\u044b: 1320 \u0445 2200 \u043c\u043c.</li>\r\n\t<li>\u0420\u0430\u0431\u043e\u0447\u0435\u0435 \u0434\u0430\u0432\u043b\u0435\u043d\u0438\u0435 \u0432\u043e\u0437\u0434\u0443\u0445\u0430: 0,55 \u041c\u041f\u0430.</li>\r\n\t<li>\u0420\u0430\u0441\u0445\u043e\u0434 \u0441\u0436\u0430\u0442\u043e\u0433\u043e \u0432\u043e\u0437\u0434\u0443\u0445\u0430: 0,3 \u043c&sup3; / \u043c\u0438\u043d.</li>\r\n\t<li>\u0421\u043a\u043e\u0440\u043e\u0441\u0442\u044c \u0432\u0441\u0430\u0441\u044b\u0432\u0430\u0435\u043c\u043e\u0433\u043e \u0432\u043e\u0437\u0434\u0443\u0445\u0430: 25 - 30 \u043c / \u0441.</li>\r\n\t<li>\u0413\u0430\u0431\u0430\u0440\u0438\u0442\u043d\u044b\u0435 \u0440\u0430\u0437\u043c\u0435\u0440\u044b: 2200 \u0445 2650 \u0445 2100 \u043c\u043c.</li>\r\n\t<li>\u0412\u0435\u0441 \u043d\u0435\u0442\u0442\u043e: 3600 \u043a\u0433.</li>\r\n</ul>", "long_description_en": "<p><strong>Wide belt sanding machine US-R-RP1300.</strong></p>\r\n\r\n<p><strong>Technical parameters of the equipment:</strong></p>\r\n\r\n<ul>\r\n\t<li>Model: US-R-RP1300.</li>\r\n\t<li>Total motor power: 63.55 KW.</li>\r\n\t<li>The length of sanding: &ge; 640 mm.</li>\r\n\t<li>The width of&nbsp;&nbsp; &nbsp;sanding: 40 ~ 1300 mm.</li>\r\n\t<li>Working thickness: 2.5 ~ 100 mm.</li>\r\n\t<li>No.1 abrasive belt speed: 20 m / sec.</li>\r\n\t<li>No.2 abrasive belt speed: 18.5 m / sec.</li>\r\n\t<li>Feed speed: 6 ~ 30 m / min.</li>\r\n\t<li>Size of abrasive belt: 1320 x 2200 mm.</li>\r\n\t<li>Working air pressure: 0.55 mpa.</li>\r\n\t<li>Consumption of compressed air: 0.3 m&sup3; / min.</li>\r\n\t<li>Speed of sucked air: 25 - 30 m / s.</li>\r\n\t<li>Overall dimension: 2200 x 2650 x 2100 mm.</li>\r\n\t<li>Net weight: 3600 kg.</li>\r\n</ul>", "price_title": null, "price_title_uz": null, "price_title_ru": null, "price_title_en": null, "price_image": null, "price_short_description": null, "price_short_description_uz": null, "price_short_description_ru": null, "price_short_description_en": null, "price_long_description": null, "price_long_description_uz": null, "price_long_description_ru": null, "price_long_description_en": null, "video": null, "view_count": 2479, "created_at": "2022-12-21T13:54:32.163000+05:00", "country": 1, "product_id": 818}