{"sku": 712, "category": {"id": 13, "category": "Packing equipment", "category_uz": "Qadoqlash uskunalari", "category_ru": "\u041e\u0431\u043e\u0440\u0443\u0434\u043e\u0432\u0430\u043d\u0438\u0435 \u0434\u043b\u044f \u0443\u043f\u0430\u043a\u043e\u0432\u043a\u0438", "category_en": "Packing equipment", "image": "https://api.uskunalar.uz/media/category_image/packing.svg", "my_order": 8, "created_at": "2022-04-14T16:26:52.494000+05:00"}, "subcategory": {"id": 719, "image": null, "subcategory": "Vertical packaging equipment", "subcategory_uz": "Vertikal qadoqlash uskunasi", "subcategory_ru": "\u0412\u0435\u0440\u0442\u0438\u043a\u0430\u043b\u044c\u043d\u043e\u0435 \u0443\u043f\u0430\u043a\u043e\u0432\u043e\u0447\u043d\u043e\u0435 \u043e\u0431\u043e\u0440\u0443\u0434\u043e\u0432\u0430\u043d\u0438\u0435", "subcategory_en": "Vertical packaging equipment", "my_order": 434, "created_at": "2022-09-14T14:11:57.954000+05:00", "category": 13, "category_uz": 13, "category_ru": 13, "category_en": 13}, "background": {"color": "Sariq", "image": "https://api.uskunalar.uz/media/banner_back/yellow.svg"}, "specifications": [{"id": 4516, "product_customer": "Model", "product_customer_uz": "Model", "product_customer_ru": "\u041c\u043e\u0434\u0435\u043b\u044c", "product_customer_en": "Model", "product_number": "US-JS-320C", "product_number_uz": "US-JS-320C", "product_number_ru": "US-JS-320C", "product_number_en": "US-JS-320C", "product_image": null}, {"id": 4517, "product_customer": "Speed", "product_customer_uz": "Tezligi", "product_customer_ru": "\u0421\u043a\u043e\u0440\u043e\u0441\u0442\u044c", "product_customer_en": "Speed", "product_number": "30-60 packs/min", "product_number_uz": "30-60qadoq/min", "product_number_ru": "30-60 \u0443\u043f\u0430\u043a\u043e\u0432\u043e\u043a/\u043c\u0438\u043d", "product_number_en": "30-60 packs/min", "product_image": null}, {"id": 4518, "product_customer": "Power", "product_customer_uz": "Quvvati", "product_customer_ru": "\u041c\u043e\u0449\u043d\u043e\u0441\u0442\u044c", "product_customer_en": "Power", "product_number": "1.2KW", "product_number_uz": "1.2KW", "product_number_ru": "1.2\u043a\u0412\u0442", "product_number_en": "1.2KW", "product_image": null}, {"id": 4519, "product_customer": "Power supply", "product_customer_uz": "Kuchlanishi", "product_customer_ru": "\u041d\u0430\u043f\u0440\u044f\u0436\u0435\u043d\u0438\u0435", "product_customer_en": "Power supply", "product_number": "220V", "product_number_uz": "220V", "product_number_ru": "220\u0412", "product_number_en": "220V", "product_image": null}], "images": [{"id": 2327, "image": "https://api.uskunalar.uz/media/products/Kukun_qadoqlash_uskunasi_320C-removebg-preview.png"}, {"id": 2328, "image": "https://api.uskunalar.uz/media/products/image-removebg-preview_4_eygAf9g.png"}], "title": "Vertical powder packing equipment US-JS-320C", "title_uz": "Vertikal kukun qadoqlash uskunasi US-JS-320C", "title_ru": "\u0412\u0435\u0440\u0442\u0438\u043a\u0430\u043b\u044c\u043d\u043e\u0435 \u043e\u0431\u043e\u0440\u0443\u0434\u043e\u0432\u0430\u043d\u0438\u0435 \u0434\u043b\u044f \u0443\u043f\u0430\u043a\u043e\u0432\u043a\u0438 \u043f\u043e\u0440\u043e\u0448\u043a\u043e\u0432 US-JS-320C", "title_en": "Vertical powder packing equipment US-JS-320C", "pdf": null, "city": null, "city_uz": null, "city_ru": null, "city_en": null, "CIP": false, "DAF": false, "EXW": true, "FCA": false, "price": "3700", "discount": "0", "inbox": "", "delivery": "Buyurtma orqali", "short_description": "The field that is inextricably linked with the manufacturing industry is packaging. There are also different directions in the field of packaging, such as powder, liquid and granule packaging. This equipment is used for powder packaging and the production speed is 30-60 packs per minute. The power of the equipment, whose voltage is 220V, is 1.2KW.", "short_description_uz": "Ishlab chiqarish sanoati bilan uzviy bog'liq bo'lgan soha bu qadoqlashdir. Qadoqlash sohasida ham turli xil yo'nalishlar bor, masalan, kukun, suyuqlik va granula qadoqlashdir. Ushbu uskuna kukun qadoqlash uchun xizmat qiladi va ishlab chiqarish tezligi daqiqasiga 30-60qadoqni tashkil  etadi. Kuchlanishi 220V ni tashkil etuvchi uskunaning quvvati 1.2KW ni tashkil etadi.", "short_description_ru": "\u0421\u0444\u0435\u0440\u0430, \u043d\u0435\u0440\u0430\u0437\u0440\u044b\u0432\u043d\u043e \u0441\u0432\u044f\u0437\u0430\u043d\u043d\u0430\u044f \u0441 \u043e\u0431\u0440\u0430\u0431\u0430\u0442\u044b\u0432\u0430\u044e\u0449\u0435\u0439 \u043f\u0440\u043e\u043c\u044b\u0448\u043b\u0435\u043d\u043d\u043e\u0441\u0442\u044c\u044e, \u2014 \u0443\u043f\u0430\u043a\u043e\u0432\u043a\u0430. \u0422\u0430\u043a\u0436\u0435 \u0441\u0443\u0449\u0435\u0441\u0442\u0432\u0443\u044e\u0442 \u0440\u0430\u0437\u043d\u044b\u0435 \u043d\u0430\u043f\u0440\u0430\u0432\u043b\u0435\u043d\u0438\u044f \u0432 \u043e\u0431\u043b\u0430\u0441\u0442\u0438 \u0443\u043f\u0430\u043a\u043e\u0432\u043a\u0438, \u0442\u0430\u043a\u0438\u0435 \u043a\u0430\u043a \u0443\u043f\u0430\u043a\u043e\u0432\u043a\u0430 \u043f\u043e\u0440\u043e\u0448\u043a\u0430, \u0436\u0438\u0434\u043a\u043e\u0441\u0442\u0438 \u0438 \u0433\u0440\u0430\u043d\u0443\u043b. \u042d\u0442\u043e \u043e\u0431\u043e\u0440\u0443\u0434\u043e\u0432\u0430\u043d\u0438\u0435 \u0438\u0441\u043f\u043e\u043b\u044c\u0437\u0443\u0435\u0442\u0441\u044f \u0434\u043b\u044f \u0443\u043f\u0430\u043a\u043e\u0432\u043a\u0438 \u043f\u043e\u0440\u043e\u0448\u043a\u043e\u0432, \u0430 \u0441\u043a\u043e\u0440\u043e\u0441\u0442\u044c \u043f\u0440\u043e\u0438\u0437\u0432\u043e\u0434\u0441\u0442\u0432\u0430 \u0441\u043e\u0441\u0442\u0430\u0432\u043b\u044f\u0435\u0442 30-60 \u0443\u043f\u0430\u043a\u043e\u0432\u043e\u043a \u0432 \u043c\u0438\u043d\u0443\u0442\u0443. \u041c\u043e\u0449\u043d\u043e\u0441\u0442\u044c \u043e\u0431\u043e\u0440\u0443\u0434\u043e\u0432\u0430\u043d\u0438\u044f, \u043d\u0430\u043f\u0440\u044f\u0436\u0435\u043d\u0438\u0435 \u043a\u043e\u0442\u043e\u0440\u043e\u0433\u043e 220\u0412, \u0441\u043e\u0441\u0442\u0430\u0432\u043b\u044f\u0435\u0442 1,2\u043a\u0412\u0442.", "short_description_en": "The field that is inextricably linked with the manufacturing industry is packaging. There are also different directions in the field of packaging, such as powder, liquid and granule packaging. This equipment is used for powder packaging and the production speed is 30-60 packs per minute. The power of the equipment, whose voltage is 220V, is 1.2KW.", "long_description": "<p>The field that is inextricably linked with the manufacturing industry is packaging. There are also different directions in the field of packaging, such as powder, liquid and granule packaging. This equipment is used for powder packaging and the production speed is 30-60 packs per minute. The power of the equipment, whose voltage is 220V, is 1.2KW.</p>\r\n\r\n<p>&nbsp;</p>\r\n\r\n<p><img alt=\"Vertical powder packing equipment US-JS-320C\" src=\"/media/uploads/2023/08/01/kukun-qadoqlash-uskunasi-320c.png\" style=\"height:100%; width:100%\" /></p>\r\n\r\n<p>&nbsp;</p>\r\n\r\n<p>&nbsp;</p>\r\n\r\n<table border=\"1\" cellpadding=\"1\" cellspacing=\"1\" style=\"width:100%\">\r\n\t<tbody>\r\n\t\t<tr>\r\n\t\t\t<td colspan=\"2\" style=\"background-color:#000000; text-align:center\"><span style=\"color:#ffffff\"><strong>General parameters</strong></span></td>\r\n\t\t</tr>\r\n\t\t<tr>\r\n\t\t\t<td><strong>Measuring range</strong></td>\r\n\t\t\t<td>50-500g</td>\r\n\t\t</tr>\r\n\t\t<tr>\r\n\t\t\t<td><strong>Packing speed</strong></td>\r\n\t\t\t<td>30-60package/min</td>\r\n\t\t</tr>\r\n\t\t<tr>\r\n\t\t\t<td><strong>Package length</strong></td>\r\n\t\t\t<td>30-200mm</td>\r\n\t\t</tr>\r\n\t\t<tr>\r\n\t\t\t<td><strong>Packing width</strong></td>\r\n\t\t\t<td>30-150mm</td>\r\n\t\t</tr>\r\n\t\t<tr>\r\n\t\t\t<td><strong>Voltage</strong></td>\r\n\t\t\t<td>220V</td>\r\n\t\t</tr>\r\n\t\t<tr>\r\n\t\t\t<td><strong>Power</strong></td>\r\n\t\t\t<td>1.2KW</td>\r\n\t\t</tr>\r\n\t\t<tr>\r\n\t\t\t<td><strong>Dimension</strong></td>\r\n\t\t\t<td>900*1100*1700</td>\r\n\t\t</tr>\r\n\t\t<tr>\r\n\t\t\t<td><strong>Weight</strong></td>\r\n\t\t\t<td>400kg</td>\r\n\t\t</tr>\r\n\t</tbody>\r\n</table>", "long_description_uz": "<p>Ishlab chiqarish sanoati bilan uzviy bog&#39;liq bo&#39;lgan soha bu qadoqlashdir. Qadoqlash sohasida ham turli xil yo&#39;nalishlar bor, masalan, kukun, suyuqlik va granula qadoqlashdir. Ushbu uskuna kukun qadoqlash uchun xizmat qiladi va ishlab chiqarish tezligi daqiqasiga 30-60qadoqni tashkil &nbsp;etadi. Kuchlanishi 220V ni tashkil etuvchi uskunaning quvvati 1.2KW ni tashkil etadi.</p>\r\n\r\n<p>&nbsp;</p>\r\n\r\n<p><img alt=\"Vertikal kukun qadoqlash uskunasi US-JS-320C\" src=\"/media/uploads/2023/08/01/kukun-qadoqlash-uskunasi-320c.png\" style=\"height:100%; width:100%\" /></p>\r\n\r\n<p>&nbsp;</p>\r\n\r\n<p>&nbsp;</p>\r\n\r\n<table border=\"1\" cellpadding=\"1\" cellspacing=\"1\" style=\"width:100%\">\r\n\t<tbody>\r\n\t\t<tr>\r\n\t\t\t<td colspan=\"2\" style=\"background-color:#000000; text-align:center\"><span style=\"color:#ffffff\"><strong>Umumiy parametrlar</strong></span></td>\r\n\t\t</tr>\r\n\t\t<tr>\r\n\t\t\t<td><strong>O&#39;lchash oralig&#39;i</strong></td>\r\n\t\t\t<td>50-500g</td>\r\n\t\t</tr>\r\n\t\t<tr>\r\n\t\t\t<td><strong>Qaqdoqlash tezligi</strong></td>\r\n\t\t\t<td>30-60qadoq/min</td>\r\n\t\t</tr>\r\n\t\t<tr>\r\n\t\t\t<td><strong>Qadoq uzunligi</strong></td>\r\n\t\t\t<td>30-200mm</td>\r\n\t\t</tr>\r\n\t\t<tr>\r\n\t\t\t<td><strong>Qadoq kengligi&nbsp;</strong></td>\r\n\t\t\t<td>30-150mm</td>\r\n\t\t</tr>\r\n\t\t<tr>\r\n\t\t\t<td><strong>Kuchlanishi</strong></td>\r\n\t\t\t<td>220V</td>\r\n\t\t</tr>\r\n\t\t<tr>\r\n\t\t\t<td><strong>Quvvati</strong></td>\r\n\t\t\t<td>1.2KW</td>\r\n\t\t</tr>\r\n\t\t<tr>\r\n\t\t\t<td><strong>O&#39;lchami</strong></td>\r\n\t\t\t<td>900*1100*1700</td>\r\n\t\t</tr>\r\n\t\t<tr>\r\n\t\t\t<td><strong>Uskuna vazni</strong></td>\r\n\t\t\t<td>400kg</td>\r\n\t\t</tr>\r\n\t</tbody>\r\n</table>", "long_description_ru": "<p>\u0421\u0444\u0435\u0440\u0430, \u043d\u0435\u0440\u0430\u0437\u0440\u044b\u0432\u043d\u043e \u0441\u0432\u044f\u0437\u0430\u043d\u043d\u0430\u044f \u0441 \u043e\u0431\u0440\u0430\u0431\u0430\u0442\u044b\u0432\u0430\u044e\u0449\u0435\u0439 \u043f\u0440\u043e\u043c\u044b\u0448\u043b\u0435\u043d\u043d\u043e\u0441\u0442\u044c\u044e, &mdash; \u0443\u043f\u0430\u043a\u043e\u0432\u043a\u0430. \u0422\u0430\u043a\u0436\u0435 \u0441\u0443\u0449\u0435\u0441\u0442\u0432\u0443\u044e\u0442 \u0440\u0430\u0437\u043d\u044b\u0435 \u043d\u0430\u043f\u0440\u0430\u0432\u043b\u0435\u043d\u0438\u044f \u0432 \u043e\u0431\u043b\u0430\u0441\u0442\u0438 \u0443\u043f\u0430\u043a\u043e\u0432\u043a\u0438, \u0442\u0430\u043a\u0438\u0435 \u043a\u0430\u043a \u0443\u043f\u0430\u043a\u043e\u0432\u043a\u0430 \u043f\u043e\u0440\u043e\u0448\u043a\u0430, \u0436\u0438\u0434\u043a\u043e\u0441\u0442\u0438 \u0438 \u0433\u0440\u0430\u043d\u0443\u043b. \u042d\u0442\u043e \u043e\u0431\u043e\u0440\u0443\u0434\u043e\u0432\u0430\u043d\u0438\u0435 \u0438\u0441\u043f\u043e\u043b\u044c\u0437\u0443\u0435\u0442\u0441\u044f \u0434\u043b\u044f \u0443\u043f\u0430\u043a\u043e\u0432\u043a\u0438 \u043f\u043e\u0440\u043e\u0448\u043a\u043e\u0432, \u0430 \u0441\u043a\u043e\u0440\u043e\u0441\u0442\u044c \u043f\u0440\u043e\u0438\u0437\u0432\u043e\u0434\u0441\u0442\u0432\u0430 \u0441\u043e\u0441\u0442\u0430\u0432\u043b\u044f\u0435\u0442 30-60 \u0443\u043f\u0430\u043a\u043e\u0432\u043e\u043a \u0432 \u043c\u0438\u043d\u0443\u0442\u0443. \u041c\u043e\u0449\u043d\u043e\u0441\u0442\u044c \u043e\u0431\u043e\u0440\u0443\u0434\u043e\u0432\u0430\u043d\u0438\u044f, \u043d\u0430\u043f\u0440\u044f\u0436\u0435\u043d\u0438\u0435 \u043a\u043e\u0442\u043e\u0440\u043e\u0433\u043e 220\u0412, \u0441\u043e\u0441\u0442\u0430\u0432\u043b\u044f\u0435\u0442 1,2\u043a\u0412\u0442.</p>\r\n\r\n<p>&nbsp;</p>\r\n\r\n<p><img alt=\"\u0412\u0435\u0440\u0442\u0438\u043a\u0430\u043b\u044c\u043d\u043e\u0435 \u043e\u0431\u043e\u0440\u0443\u0434\u043e\u0432\u0430\u043d\u0438\u0435 \u0434\u043b\u044f \u0443\u043f\u0430\u043a\u043e\u0432\u043a\u0438 \u043f\u043e\u0440\u043e\u0448\u043a\u043e\u0432 US-JS-320C\" src=\"/media/uploads/2023/08/01/kukun-qadoqlash-uskunasi-320c.png\" style=\"height:100%; width:100%\" /></p>\r\n\r\n<p>&nbsp;</p>\r\n\r\n<table border=\"1\" cellpadding=\"1\" cellspacing=\"1\" style=\"width:100%\">\r\n\t<tbody>\r\n\t\t<tr>\r\n\t\t\t<td colspan=\"2\" style=\"background-color:#000000; text-align:center\"><span style=\"color:#ffffff\"><strong>\u041e\u0431\u0449\u0438\u0435 \u043f\u0430\u0440\u0430\u043c\u0435\u0442\u0440\u044b</strong></span></td>\r\n\t\t</tr>\r\n\t\t<tr>\r\n\t\t\t<td><strong>\u0414\u0438\u0430\u043f\u0430\u0437\u043e\u043d \u0438\u0437\u043c\u0435\u0440\u0435\u043d\u0438\u044f</strong></td>\r\n\t\t\t<td>50-500\u0433</td>\r\n\t\t</tr>\r\n\t\t<tr>\r\n\t\t\t<td><strong>\u0421\u043a\u043e\u0440\u043e\u0441\u0442\u044c \u0443\u043f\u0430\u043a\u043e\u0432\u043a\u0438</strong></td>\r\n\t\t\t<td>30-60 \u0443\u043f\u0430\u043a\u043e\u0432\u043e\u043a/\u043c\u0438\u043d</td>\r\n\t\t</tr>\r\n\t\t<tr>\r\n\t\t\t<td><strong>\u0414\u043b\u0438\u043d\u0430 \u0443\u043f\u0430\u043a\u043e\u0432\u043a\u0438</strong></td>\r\n\t\t\t<td>30-200\u043c\u043c</td>\r\n\t\t</tr>\r\n\t\t<tr>\r\n\t\t\t<td><strong>\u0428\u0438\u0440\u0438\u043d\u0430 \u0443\u043f\u0430\u043a\u043e\u0432\u043a\u0438</strong></td>\r\n\t\t\t<td>30-150\u043c\u043c</td>\r\n\t\t</tr>\r\n\t\t<tr>\r\n\t\t\t<td><strong>\u041d\u0430\u043f\u0440\u044f\u0436\u0435\u043d\u0438\u0435</strong></td>\r\n\t\t\t<td>220\u0412</td>\r\n\t\t</tr>\r\n\t\t<tr>\r\n\t\t\t<td><strong>\u041c\u043e\u0449\u043d\u043e\u0441\u0442\u044c</strong></td>\r\n\t\t\t<td>1,2 \u043a\u0412\u0442</td>\r\n\t\t</tr>\r\n\t\t<tr>\r\n\t\t\t<td><strong>\u0420\u0430\u0437\u043c\u0435\u0440</strong></td>\r\n\t\t\t<td>900*1100*1700</td>\r\n\t\t</tr>\r\n\t\t<tr>\r\n\t\t\t<td><strong>\u041c\u0430\u0441\u0441\u0430 \u043e\u0431\u043e\u0440\u0443\u0434\u043e\u0432\u0430\u043d\u0438\u044f</strong></td>\r\n\t\t\t<td>400 \u043a\u0433</td>\r\n\t\t</tr>\r\n\t</tbody>\r\n</table>", "long_description_en": "<p>The field that is inextricably linked with the manufacturing industry is packaging. There are also different directions in the field of packaging, such as powder, liquid and granule packaging. This equipment is used for powder packaging and the production speed is 30-60 packs per minute. The power of the equipment, whose voltage is 220V, is 1.2KW.</p>\r\n\r\n<p>&nbsp;</p>\r\n\r\n<p><img alt=\"Vertical powder packing equipment US-JS-320C\" src=\"/media/uploads/2023/08/01/kukun-qadoqlash-uskunasi-320c.png\" style=\"height:100%; width:100%\" /></p>\r\n\r\n<p>&nbsp;</p>\r\n\r\n<p>&nbsp;</p>\r\n\r\n<table border=\"1\" cellpadding=\"1\" cellspacing=\"1\" style=\"width:100%\">\r\n\t<tbody>\r\n\t\t<tr>\r\n\t\t\t<td colspan=\"2\" style=\"background-color:#000000; text-align:center\"><span style=\"color:#ffffff\"><strong>General parameters</strong></span></td>\r\n\t\t</tr>\r\n\t\t<tr>\r\n\t\t\t<td><strong>Measuring range</strong></td>\r\n\t\t\t<td>50-500g</td>\r\n\t\t</tr>\r\n\t\t<tr>\r\n\t\t\t<td><strong>Packing speed</strong></td>\r\n\t\t\t<td>30-60package/min</td>\r\n\t\t</tr>\r\n\t\t<tr>\r\n\t\t\t<td><strong>Package length</strong></td>\r\n\t\t\t<td>30-200mm</td>\r\n\t\t</tr>\r\n\t\t<tr>\r\n\t\t\t<td><strong>Packing width</strong></td>\r\n\t\t\t<td>30-150mm</td>\r\n\t\t</tr>\r\n\t\t<tr>\r\n\t\t\t<td><strong>Voltage</strong></td>\r\n\t\t\t<td>220V</td>\r\n\t\t</tr>\r\n\t\t<tr>\r\n\t\t\t<td><strong>Power</strong></td>\r\n\t\t\t<td>1.2KW</td>\r\n\t\t</tr>\r\n\t\t<tr>\r\n\t\t\t<td><strong>Dimension</strong></td>\r\n\t\t\t<td>900*1100*1700</td>\r\n\t\t</tr>\r\n\t\t<tr>\r\n\t\t\t<td><strong>Weight</strong></td>\r\n\t\t\t<td>400kg</td>\r\n\t\t</tr>\r\n\t</tbody>\r\n</table>", "price_title": null, "price_title_uz": null, "price_title_ru": null, "price_title_en": null, "price_image": null, "price_short_description": null, "price_short_description_uz": null, "price_short_description_ru": null, "price_short_description_en": null, "price_long_description": null, "price_long_description_uz": null, "price_long_description_ru": null, "price_long_description_en": null, "video": null, "view_count": 1138, "created_at": "2023-08-01T15:00:07.432354+05:00", "country": 1, "product_id": 629}